[
  {
    "decided_at": "2026-07-01T04:24:16.370984+00:00",
    "market": "btc-updown-5m-1782879600",
    "window_start": 1782879600,
    "window_end": 1782879900,
    "side": "Up",
    "token_id": "29857350112570736152946196883601540991804522776805776680005274988519359916832",
    "entry_price": 0.51,
    "shares": 335.7,
    "model_prob": 0.9987,
    "edge": 0.4887,
    "price_to_beat": 59108.29292196449,
    "stake": 171.207,
    "stopped": false,
    "stop_proceeds": null,
    "stop_price": null
  }
]