[
  {
    "decided_at": "2026-06-20T06:49:35.436524+00:00",
    "market": "btc-updown-5m-1781937900",
    "window_start": 1781937900,
    "window_end": 1781938200,
    "side": "Down",
    "token_id": "110929789525033557302030825968842969611391481658329950551480479784737745397401",
    "entry_price": 0.57,
    "shares": 3.62,
    "model_prob": 0.8502,
    "edge": 0.2802,
    "price_to_beat": 63689.42142489277,
    "stake": 2.0634,
    "stopped": false,
    "stop_proceeds": null,
    "stop_price": null
  }
]