[
  {
    "decided_at": "2026-06-25T10:54:15.543299+00:00",
    "market": "btc-updown-5m-1782384600",
    "window_start": 1782384600,
    "window_end": 1782384900,
    "side": "Up",
    "token_id": "100691069250464833080304441395065578545379702012732539428229780805203843091345",
    "entry_price": 0.81,
    "shares": 223.95,
    "model_prob": 0.9306,
    "edge": 0.1206,
    "price_to_beat": 61250.33632999299,
    "stake": 181.3995,
    "stopped": false,
    "stop_proceeds": null,
    "stop_price": null
  }
]