[
  {
    "decided_at": "2026-06-19T01:44:16.182699+00:00",
    "market": "btc-updown-5m-1781833200",
    "window_start": 1781833200,
    "window_end": 1781833500,
    "side": "Up",
    "token_id": "55196072064259664519589220861007978596402833534476603698410098193763796224629",
    "entry_price": 0.94,
    "shares": 956.76,
    "model_prob": 0.9927,
    "edge": 0.0527,
    "price_to_beat": 62820.241625607,
    "stake": 899.3544,
    "stopped": false,
    "stop_proceeds": null,
    "stop_price": null
  }
]