[
  {
    "decided_at": "2026-06-29T03:44:52.147101+00:00",
    "market": "btc-updown-5m-1782704400",
    "window_start": 1782704400,
    "window_end": 1782704700,
    "side": "Up",
    "token_id": "111577080226505819247183253381426653921699748021394306868588624679651357541109",
    "entry_price": 0.4,
    "shares": 40.48,
    "model_prob": 0.9066,
    "edge": 0.5066,
    "price_to_beat": 59816.47213423409,
    "stake": 16.192,
    "stopped": false,
    "stop_proceeds": null,
    "stop_price": null
  }
]