[
  {
    "decided_at": "2026-06-23T01:34:34.699310+00:00",
    "market": "btc-updown-5m-1782178200",
    "window_start": 1782178200,
    "window_end": 1782178500,
    "side": "Down",
    "token_id": "15629027256278152295005505072905394159684573396328735175631803345117131830547",
    "entry_price": 0.79,
    "shares": 245.15,
    "model_prob": 0.9538,
    "edge": 0.1638,
    "price_to_beat": 64123.16413,
    "stake": 193.6685,
    "stopped": false,
    "stop_proceeds": null,
    "stop_price": null
  }
]