[
  {
    "decided_at": "2026-06-27T09:59:17.545638+00:00",
    "market": "btc-updown-5m-1782554100",
    "window_start": 1782554100,
    "window_end": 1782554400,
    "side": "Up",
    "token_id": "83202185647119267928640720941221341182785712566800849973680968249111071019350",
    "entry_price": 0.63,
    "shares": 19.44,
    "model_prob": 0.9988,
    "edge": 0.3688,
    "price_to_beat": 60314.73349605074,
    "stake": 12.2472,
    "stopped": false,
    "stop_proceeds": null,
    "stop_price": null
  }
]