[
  {
    "decided_at": "2026-06-21T05:59:23.141875+00:00",
    "market": "btc-updown-5m-1782021300",
    "window_start": 1782021300,
    "window_end": 1782021600,
    "side": "Up",
    "token_id": "48359267728260386044837293174378711739345858991763268816390118330869238512075",
    "entry_price": 0.75,
    "shares": 274.93,
    "model_prob": 0.8573,
    "edge": 0.1073,
    "price_to_beat": 64171.04613353712,
    "stake": 206.1975,
    "stopped": false,
    "stop_proceeds": null,
    "stop_price": null
  }
]