[
  {
    "decided_at": "2026-06-17T21:19:15.689260+00:00",
    "market": "btc-updown-5m-1781730900",
    "window_start": 1781730900,
    "window_end": 1781731200,
    "side": "Down",
    "token_id": "113204299511269232062791296819908548710697130980941689244390441208290996004744",
    "entry_price": 0.93,
    "shares": 20.02,
    "model_prob": 0.9999,
    "edge": 0.0699,
    "price_to_beat": 64274.79489780448,
    "stake": 18.6186,
    "stopped": false,
    "stop_proceeds": null,
    "stop_price": null
  }
]