[
  {
    "decided_at": "2026-06-19T23:44:17.704976+00:00",
    "market": "btc-updown-5m-1781912400",
    "window_start": 1781912400,
    "window_end": 1781912700,
    "side": "Down",
    "token_id": "69319684738009631311980874103334453110534387405193784460955663291870111038304",
    "entry_price": 0.55,
    "shares": 83.27,
    "model_prob": 0.9967,
    "edge": 0.4467,
    "price_to_beat": 63276.11479728134,
    "stake": 45.7985,
    "stopped": false,
    "stop_proceeds": null,
    "stop_price": null
  }
]