[
  {
    "decided_at": "2026-06-14T01:54:27.338250+00:00",
    "market": "btc-updown-5m-1781401800",
    "window_start": 1781401800,
    "window_end": 1781402100,
    "side": "Down",
    "token_id": "65774153103405561704518348613639659999745073877558859953852398369110904907492",
    "entry_price": 0.86,
    "shares": 17.06,
    "model_prob": 0.9825,
    "edge": 0.1225,
    "price_to_beat": 64608.76049952372,
    "stake": 14.6716,
    "stopped": false,
    "stop_proceeds": null,
    "stop_price": null
  }
]