[
  {
    "decided_at": "2026-06-27T11:24:16.366685+00:00",
    "market": "btc-updown-5m-1782559200",
    "window_start": 1782559200,
    "window_end": 1782559500,
    "side": "Up",
    "token_id": "31237529639040577577159732040697904546954183183816213943120168180772314587204",
    "entry_price": 0.87,
    "shares": 214.2,
    "model_prob": 0.9948,
    "edge": 0.1248,
    "price_to_beat": 60235.89912279199,
    "stake": 186.354,
    "stopped": false,
    "stop_proceeds": null,
    "stop_price": null
  }
]