[
  {
    "decided_at": "2026-06-09T08:19:23.869948+00:00",
    "market": "btc-updown-5m-1780992900",
    "window_start": 1780992900,
    "window_end": 1780993200,
    "side": "Up",
    "token_id": "3198562979644265739644128350448124994936958055161506697286418554631556088258",
    "entry_price": 0.45,
    "shares": 16.0865,
    "model_prob": 0.858,
    "edge": 0.408,
    "price_to_beat": 62874.500595,
    "stake": 7.2389,
    "stopped": true,
    "stop_proceeds": 5.7911,
    "stop_price": 0.36
  }
]