[
  {
    "decided_at": "2026-06-10T21:19:18.241381+00:00",
    "market": "btc-updown-5m-1781126100",
    "window_start": 1781126100,
    "window_end": 1781126400,
    "side": "Up",
    "token_id": "112871737424393906563241454943310536381742640324232781790761923615674669383700",
    "entry_price": 0.88,
    "shares": 29.662,
    "model_prob": 0.9446,
    "edge": 0.0646,
    "price_to_beat": 61474.531549320425,
    "stake": 26.1026,
    "stopped": false,
    "stop_proceeds": null,
    "stop_price": null
  }
]