[
  {
    "decided_at": "2026-06-25T19:59:16.451997+00:00",
    "market": "btc-updown-5m-1782417300",
    "window_start": 1782417300,
    "window_end": 1782417600,
    "side": "Up",
    "token_id": "23880049507013142854390097047226320843298987802227032998331676520640258778512",
    "entry_price": 0.08,
    "shares": 328.56,
    "model_prob": 0.9972,
    "edge": 0.9172,
    "price_to_beat": 59204.59200919356,
    "stake": 26.2848,
    "stopped": false,
    "stop_proceeds": null,
    "stop_price": null
  }
]