[
  {
    "decided_at": "2026-06-14T07:54:15.890876+00:00",
    "market": "btc-updown-5m-1781423400",
    "window_start": 1781423400,
    "window_end": 1781423700,
    "side": "Up",
    "token_id": "4242645982974541267353145326329817365723108255322520145716065433704030719506",
    "entry_price": 0.62,
    "shares": 301.07,
    "model_prob": 0.926,
    "edge": 0.306,
    "price_to_beat": 64370.03015452925,
    "stake": 186.6634,
    "stopped": false,
    "stop_proceeds": null,
    "stop_price": null
  }
]